crystalball/__init__.py
crystal_ball-0.1.9.dist-info/LICENSE.txt
crystal_ball-0.1.9.dist-info/METADATA
crystal_ball-0.1.9.dist-info/WHEEL
crystal_ball-0.1.9.dist-info/top_level.txt
crystal_ball-0.1.9.dist-info/RECORD
