Metadata-Version: 2.1
Name: crystal-ball
Version: 0.1.9
Summary: Useful crystal-ball-related stuff.
Home-page: http://pypi.python.org/pypi/crystal-ball/
Author: Winn Y Cui
Author-email: winn.yc@berkeley.edu
License: LICENSE.txt
Platform: UNKNOWN
Classifier: Programming Language :: Python :: 3
Classifier: License :: OSI Approved :: MIT License
Classifier: Operating System :: OS Independent
Requires-Dist: pandas
Requires-Dist: seaborn
